Jenkinsfile
MANIFEST.in
README.rst
setup.py
buildouts/plone4/buildout.cfg
buildouts/plone4/install.sh
buildouts/plone4/versions.cfg
docs/HISTORY.txt
docs/LICENSE.GPL
docs/LICENSE.txt
eea/__init__.py
eea.epub.egg-info/PKG-INFO
eea.epub.egg-info/SOURCES.txt
eea.epub.egg-info/dependency_links.txt
eea.epub.egg-info/entry_points.txt
eea.epub.egg-info/namespace_packages.txt
eea.epub.egg-info/not-zip-safe
eea.epub.egg-info/requires.txt
eea.epub.egg-info/top_level.txt
eea/epub/__init__.py
eea/epub/async.py
eea/epub/config.py
eea/epub/configure.zcml
eea/epub/interfaces.py
eea/epub/mimetype.py
eea/epub/permissions.zcml
eea/epub/profiles.zcml
eea/epub/version.txt
eea/epub/browser/__init__.py
eea/epub/browser/configure.zcml
eea/epub/browser/epub_toc_logic.py
eea/epub/browser/epub_utils.py
eea/epub/browser/events.py
eea/epub/browser/import.py
eea/epub/browser/interfaces.py
eea/epub/browser/app/__init__.py
eea/epub/browser/app/body.py
eea/epub/browser/app/cover.py
eea/epub/browser/app/download.py
eea/epub/browser/app/viewlet.py
eea/epub/browser/css/view.css
eea/epub/browser/img/download-epub.png
eea/epub/browser/js/view.js
eea/epub/browser/zpt/body.pt
eea/epub/browser/zpt/download.pt
eea/epub/browser/zpt/epub.pt
eea/epub/browser/zpt/viewlet.pt
eea/epub/cache/__init__.py
eea/epub/cache/behavior.py
eea/epub/cache/cache.py
eea/epub/cache/configure.zcml
eea/epub/cache/nocache.py
eea/epub/events/__init__.py
eea/epub/events/async.py
eea/epub/events/configure.zcml
eea/epub/events/interfaces.py
eea/epub/events/subscribers.py
eea/epub/events/sync.py
eea/epub/export/__init__.py
eea/epub/export/configure.zcml
eea/epub/export/epub.py
eea/epub/export/interfaces.py
eea/epub/export/static/META-INF/container.xml
eea/epub/export/static/OEBPS/content.opf
eea/epub/export/static/OEBPS/toc.ncx
eea/epub/export/static/OEBPS/Css/fonts.css
eea/epub/export/static/OEBPS/Css/main.css
eea/epub/export/static/OEBPS/Fonts/tex-bold.ttf
eea/epub/export/static/OEBPS/Fonts/tex-bolditalic.ttf
eea/epub/export/static/OEBPS/Fonts/tex-italic.ttf
eea/epub/export/static/OEBPS/Fonts/tex-regular.ttf
eea/epub/export/static/OEBPS/Images/cross.png
eea/epub/export/static/OEBPS/Images/draft.png
eea/epub/export/static/OEBPS/Images/emoticon_smile.png
